refutil/__init__.py
refutil-1.0.2.dist-info/METADATA
refutil-1.0.2.dist-info/WHEEL
refutil-1.0.2.dist-info/top_level.txt
refutil-1.0.2.dist-info/RECORD
