Metadata-Version: 2.1
Name: refutil
Version: 1.0.2
Summary: effortless weakrefs to objects, methods, and functions with annotations
Home-page: https://github.com/ConnorSMaynes/refutil
Author: Connor Sherwood Maynes
Author-email: connormaynes@gmail.com
License: MIT
Keywords: weakref,ReferenceType
Classifier: Programming Language :: Python :: 3
Classifier: Operating System :: OS Independent
Requires-Python: >=2.5
